tests/__init__.py
tests/test_settings.py
tests/tests.py
tests/urls.py
wagtail_stacks_image/__init__.py
wagtail_stacks_image/apps.py
wagtail_stacks_image/blocks.py
wagtail_stacks_image/registered_blocks.py
wagtail_stacks_image/static/js/wagtail_stacks_image.js
wagtail_stacks_image/static/js/vendor/lazyimages/lazyimages.js
wagtail_stacks_image/static/js/vendor/owl/carousel.js
wagtail_stacks_image/static/sass/_wagtail_stacks_image.scss
wagtail_stacks_image/templates/wagtail_stacks_image/list/1up.html
wagtail_stacks_image/templates/wagtail_stacks_image/list/2up.html
wagtail_stacks_image/templates/wagtail_stacks_image/list/3up.html
wagtail_stacks_image/templates/wagtail_stacks_image/list/carousel.html
wagtail_stacks_image/templates/wagtail_stacks_image/list/list-item-carousel.html
wagtail_stacks_image/templates/wagtail_stacks_image/list/list-item.html
wagtail_stacks_image/templates/wagtail_stacks_image/single/full_width.html
wagtail_stacks_image/templates/wagtail_stacks_image/single/image_left_content_right.html
wagtail_stacks_image/templates/wagtail_stacks_image/single/image_right_content_left.html
wagtail_stacks_image-0.1.dist-info/DESCRIPTION.rst
wagtail_stacks_image-0.1.dist-info/LICENSE.txt
wagtail_stacks_image-0.1.dist-info/METADATA
wagtail_stacks_image-0.1.dist-info/RECORD
wagtail_stacks_image-0.1.dist-info/WHEEL
wagtail_stacks_image-0.1.dist-info/metadata.json
wagtail_stacks_image-0.1.dist-info/top_level.txt
