Metadata-Version: 2.0
Name: wagtail-stacks-image
Version: 0.1
Summary: A Wagtail Stacks application for handling images and lists of images.
Home-page: http://stacks.wgbhdigital.org/
Author: Jonathan Ellenberger
Author-email: jonathan_ellenberger@wgbh.org
License: MIT License, see LICENSE
Platform: UNKNOWN
Classifier: Framework :: Django
Classifier: Framework :: Django :: 1.8
Classifier: License :: OSI Approved :: MIT License
Classifier: Natural Language :: English
Classifier: Programming Language :: Python
Classifier: Programming Language :: Python :: 2
Classifier: Programming Language :: Python :: 2.7
Requires-Dist: wagtail-streamfieldtools (>=0.1)
